<?xml version="1.0" encoding="utf-8"?>
<projeto>
	<dados>
		<id><![CDATA[88]]></id>
		<id_cliente><![CDATA[22]]></id_cliente>
		<id_parceiro><![CDATA[49]]></id_parceiro>
		<id_suporte><![CDATA[2]]></id_suporte>
		<projeto_pt><![CDATA[Os riscos do protecionismo]]></projeto_pt>
		<projeto_en><![CDATA[]]></projeto_en>
		<url><![CDATA[http://veja.abril.com.br/multimidia/video/os-riscos-do-protecionismo]]></url>
		<tx_info_pt><![CDATA[<p>O governo imp&otilde;e restri&ccedil;&otilde;es aos produtos importados para defender a ind&uacute;stria local, mas a estrat&eacute;gia prejudica o consumidor e pode atrasar o desenvolvimento do pa&iacute;s.</p>]]></tx_info_pt>
		<tx_info_en><![CDATA[]]></tx_info_en>
		<tx_cred_pt><![CDATA[<p><strong>roteiro/apresenta&ccedil;&atilde;o</strong><br />Marcelo Sakate</p>
<p><strong>dire&ccedil;&atilde;o</strong><br />Alexandre Oliveira&nbsp;</p>]]></tx_cred_pt>
		<tx_cred_en><![CDATA[]]></tx_cred_en>
		<publicado_pt><![CDATA[0]]></publicado_pt>
		<publicado_en><![CDATA[]]></publicado_en>
		<data><![CDATA[2012-10-24]]></data>
		<layout><![CDATA[emb335/w_emb]]></layout>
		<sb_layout><![CDATA[sb118,sb119,sb121,sb122]]></sb_layout>
	</dados>
	<arquivos>
		<arquivo>
			<id><![CDATA[335]]></id>
			<id_proj><![CDATA[88]]></id_proj>
			<tipo><![CDATA[emb]]></tipo>
			<label_pt><![CDATA[video]]></label_pt>
			<label_en><![CDATA[]]></label_en>
			<legenda_en><![CDATA[]]></legenda_en>
			<legenda_pt><![CDATA[]]></legenda_pt>
			<tx_embed><![CDATA[<iframe src="//player.vimeo.com/video/70865794?title=0&amp;byline=0&amp;portrait=0&amp;color=ffffff" width="640" height="360" frameborder="0" webkitallowfullscreen mozallowfullscreen allowfullscreen></iframe>]]></tx_embed>
			<url><![CDATA[]]></url>
		</arquivo>
	</arquivos>
</projeto>
